electricity/__init__.py
electricity/add_residual_mix.py
electricity/config.py
electricity/create_datapackages.py
electricity/entso_data_converter.py
electricity/modify_electricity_markets.py
sensitivity_analysis/__init__.py
sensitivity_analysis/local_sensitivity_analysis.py
sensitivity_analysis/remove_non_influential.py
sensitivity_analysis/validation.py
akula-0.1.dev3.dist-info/LICENSE.txt
akula-0.1.dev3.dist-info/METADATA
akula-0.1.dev3.dist-info/WHEEL
akula-0.1.dev3.dist-info/top_level.txt
akula-0.1.dev3.dist-info/RECORD
