Metadata-Version: 2.1
Name: akula
Version: 0.1.dev3
Summary: Add a short description here!
Home-page: https://github.com/aleksandra-kim/akula/
Author: aleksandra-kim, cmutel
Author-email: aleksandra.kim@icloud.com
License: MIT
Project-URL: Documentation, https://github.com/aleksandra-kim/akula/
Platform: any
Classifier: Development Status :: 4 - Beta
Classifier: Programming Language :: Python
License-File: LICENSE.txt
Requires-Dist: brightway25 (>=1.0.6)
Requires-Dist: tqdm
Requires-Dist: thefuzz
Requires-Dist: importlib-metadata ; python_version < "3.8"
Provides-Extra: testing
Requires-Dist: setuptools ; extra == 'testing'
Requires-Dist: pytest ; extra == 'testing'
Requires-Dist: pytest-cov ; extra == 'testing'
